argumentor/__init__.py
argumentor/builder.py
argumentor/const.py
argumentor/exc.py
argumentor/helper.py
argumentor/parser.py
argumentor/std.py
argumentor-2.1.0.dist-info/licenses/LICENSE
argumentor-2.1.0.dist-info/METADATA
argumentor-2.1.0.dist-info/WHEEL
argumentor-2.1.0.dist-info/top_level.txt
argumentor-2.1.0.dist-info/RECORD
