Metadata-Version: 2.4
Name: argumentor
Version: 2.1.0
Summary: lightweight & copylefted library to work with command-line arguments
Author-email: Camelia Lavender <camelia@tblock.me>
Maintainer-email: Camelia Lavender <camelia@tblock.me>
License-Expression: LGPL-3.0-or-later
Project-URL: Homepage, https://codeberg.org/camelia/python-argumentor
Project-URL: Documentation, https://pyargumentor.camelia.dev/
Project-URL: Repository, https://codeberg.org/camelia/python-argumentor
Project-URL: Issues, https://codeberg.org/camelia/python-argumentor/issues
Project-URL: Changelog, https://codeberg.org/camelia/python-argumentor/src/branch/main/CHANGELOG.md
Classifier: Programming Language :: Python :: 3
Classifier: Programming Language :: Python :: 3.8
Classifier: Programming Language :: Python :: 3.9
Classifier: Programming Language :: Python :: 3.10
Classifier: Programming Language :: Python :: 3.11
Classifier: Programming Language :: Python :: 3.12
Requires-Python: >=3.8
License-File: LICENSE
Dynamic: license-file
